un_striping/un_stripring.v
module un_stripring
(
    input clk_2f,
	input [31:0] lane_0,
	input [31:0] lane_1,
	input valid_0,
    input valid_1,
	input reset,
	output reg [31:0] data_out,
    output reg  valid_out
);
reg selector;
always @(posedge clk_2f) 
begin
    if(reset == 1)
    begin
        selector <=0 ;
        valid_out <= 0;
        data_out <= 32'h00000000 ;
    end
    else 
    begin
        selector <= 0;
        if(valid_0 == 1 && selector == 0) 
        begin
            data_out <= lane_0 ;
            selector <= ~selector;
            valid_out <= 1;
        end

        else if(valid_1 == 1 && selector == 1) 
        begin
            data_out<=lane_1 ;
            selector <= ~selector;
            valid_out <= 1;
        end

        else if (valid_0 == 0 && selector == 0) 
        begin
            valid_out <= 0;
            selector <= ~selector; //continuar haciendo toogle aunque valid este en 0
            data_out <= 32'h00000000 ;
        end

        else if (valid_1 == 0 && selector == 1) 
        begin
            valid_out <= 0;
            selector <= ~selector; //continuar haciendo toogle aunque valid este en 0
            data_out <= 32'h00000000 ;
        end
    end
end
endmodule

un_striping/probador_un_striping.v
module probador_un_striping
( 
    input [31:0] data_out,
    input valid_out,
    input [31:0] data_out_synth,
    input valid_out_synth,
    output reg valid_0,  
    output reg valid_1,
	output reg clk_f,
    output reg clk_2f,
    output reg reset,
    output reg [31:0] lane_0,
    output reg [31:0] lane_1
);
	initial begin
	$dumpfile("unstriping.vcd");
	$dumpvars;
	valid_0 <= 0;
	valid_1 <= 0;
	reset <= 0;
	//valid_out <= 0;
	{lane_0,lane_1} <= 32'h00000000;
	@(posedge clk_2f);
	//valid_out <= 1;
	valid_0 <= 1;
	lane_0 <= 32'hFFFFFFFF;
	lane_1 <= 32'hFFFFFFFF;

	@(posedge clk_2f);
	valid_1 <= 1;
	lane_1 <= 32'hEEEEEEEE;

	@(posedge clk_2f);
	lane_0 <= 32'hDDDDDDDD;

	@(posedge clk_2f);
	lane_1 <= 32'hCCCCCCCC;

	@(posedge clk_2f);
	valid_0 <= 0;
	//valid_out <= 0;
	lane_0 <= 32'h00000000;

	@(posedge clk_2f);
	valid_1 <= 0;
	lane_1 <= 32'h00000000;

	@(posedge clk_2f);
	valid_0 <= 1;
	//valid_out <= 1;
	lane_0 <= 32'h00000003;

	@(posedge clk_2f);
	valid_1 <= 1;
	lane_1 <= 32'h00000004;

	@(posedge clk_2f);
	//valid_out <= 0;

	@(posedge clk_2f);
	reset <= 1;
	valid_0 <= 1;
	//valid_out <= 1;
	lane_0 <= 32'h00000003;

	$finish;
	end

	initial clk_f <= 0;
	always #1 clk_f <= ~clk_f;
	
	initial clk_2f <= 0;
	always #2 clk_2f <= ~clk_2f;


endmodule

un_striping/unstriping.vcd
$date
	Tue Oct  5 17:27:29 2021
$end
$version
	Icarus Verilog
$end
$timescale
	1ns
$end
$scope module probador_un_striping $end
$var wire 32 ! data_out [31:0] $end
$var wire 32 " data_out_synth [31:0] $end
$var wire 1 # valid_out $end
$var wire 1 $ valid_out_synth $end
$var reg 1 % clk_2f $end
$var reg 1 & clk_f $end
$var reg 32 ' lane_0 [31:0] $end
$var reg 32 ( lane_1 [31:0] $end
$var reg 1 ) reset $end
$var reg 1 * valid_0 $end
$var reg 1 + valid_1 $end
$upscope $end
$scope module un_stripring $end
$var wire 1 , clk_2f $end
$var wire 32 - lane_0 [31:0] $end
$var wire 32 . lane_1 [31:0] $end
$var wire 1 / reset $end
$var wire 1 0 valid_0 $end
$var wire 1 1 valid_1 $end
$var reg 32 2 data_out [31:0] $end
$var reg 1 3 selector $end
$var reg 1 4 valid_out $end
$upscope $end
$enddefinitions $end
#0
$dumpvars
x4
x3
bx 2
z1
z0
z/
bz .
bz -
z,
0+
0*
0)
b0 (
b0 '
0&
0%
z$
z#
bz "
bz !
$end
#1
1&
#2
b11111111111111111111111111111111 (
b11111111111111111111111111111111 '
1*
0&
1%
#3
1&
#4
0&
0%
#5
1&
#6
b11101110111011101110111011101110 (
1+
0&
1%
#7
1&
#8
0&
0%
#9
1&
#10
b11011101110111011101110111011101 '
0&
1%
#11
1&
#12
0&
0%
#13
1&
#14
b11001100110011001100110011001100 (
0&
1%
#15
1&
#16
0&
0%
#17
1&
#18
b0 '
0*
0&
1%
#19
1&
#20
0&
0%
#21
1&
#22
b0 (
0+
0&
1%
#23
1&
#24
0&
0%
#25
1&
#26
b11 '
1*
0&
1%
#27
1&
#28
0&
0%
#29
1&
#30
b100 (
1+
0&
1%
#31
1&
#32
0&
0%
#33
1&
#34
0&
1%
#35
1&
#36
0&
0%
#37
1&
#38
1)
0&
1%
